invoicez/__init__.py
invoicez/builder.py
invoicez/cli/__init__.py
invoicez/cli/clean.py
invoicez/cli/new.py
invoicez/cli/run.py
invoicez/config.py
invoicez/exceptions.py
invoicez/paths.py
invoicez/runner.py
invoicez/target.py
invoicez-3.1.1.dist-info/entry_points.txt
invoicez-3.1.1.dist-info/LICENSE
invoicez-3.1.1.dist-info/WHEEL
invoicez-3.1.1.dist-info/METADATA
invoicez-3.1.1.dist-info/RECORD
