Metadata-Version: 2.1
Name: invoicez
Version: 3.1.1
Summary: Tool to handle invoices.
Home-page: https://github.com/m09/invoicez
License: Apache-2.0
Author: m09
Author-email: 142691+m09@users.noreply.github.com
Requires-Python: >=3.8.1,<4.0.0
Classifier: License :: OSI Approved :: Apache Software License
Classifier: Programming Language :: Python :: 3
Classifier: Programming Language :: Python :: 3.9
Classifier: Programming Language :: Python :: 3.10
Classifier: Programming Language :: Python :: 3.11
Classifier: Topic :: Software Development :: Build Tools
Requires-Dist: GitPython (>=3.1.29,<4.0.0)
Requires-Dist: Jinja2 (>=3.1.2,<4.0.0)
Requires-Dist: PyYAML (>=6.0,<7.0)
Requires-Dist: click (>=8.1.3,<9.0.0)
Requires-Dist: coloredlogs (>=15.0.1,<16.0.0)
